animo/__init__.py
animo/client.py
animo/resources/__init__.py
animo/resources/videos.py
animo-0.1.4.dist-info/METADATA
animo-0.1.4.dist-info/WHEEL
animo-0.1.4.dist-info/RECORD
