Metadata-Version: 2.3
Name: animo
Version: 0.1.4
Summary: Create animations from text using Manim
License: MIT
Keywords: manim,animation,video,generative
Author: Marcelo
Author-email: team@animo.video
Requires-Python: >=3.9.6
Classifier: Development Status :: 4 - Beta
Classifier: Intended Audience :: Developers
Classifier: License :: OSI Approved :: MIT License
Classifier: Programming Language :: Python :: 3
Classifier: Programming Language :: Python :: 3.10
Classifier: Programming Language :: Python :: 3.11
Classifier: Programming Language :: Python :: 3.12
Classifier: Programming Language :: Python :: 3.13
Classifier: Programming Language :: Python :: 3.9
Requires-Dist: requests (>=2.31.0,<3.0.0)
Project-URL: Homepage, https://animo.video
Project-URL: Repository, https://github.com/marcelo-earth/generative-manim
